Workbook

Sheet ATTENDANCE
A2: month | B2: year | C2: Attendance sheet - August 2026 | AH2: BY avinav sinha
A3: August | B3: 2026
A4: =DATEVALUE("1"&A3&B3) -> 46235 | B4: =EOMONTH(A4,0) -> 46265
A5: EMP_ID | B5: EMP_NAME | C5: =A4 -> 46235 | D5: =IF(C5<$B$4,C5+1,"") -> 46236 | E5: =IF(D5<$B$4,D5+1,"") -> 46237 | F5: =IF(E5<$B$4,E5+1,"") -> 46238 | G5: =IF(F5<$B$4,F5+1,"") -> 46239 | H5: =IF(G5<$B$4,G5+1,"") -> 46240 | I5: =IF(H5<$B$4,H5+1,"") -> 46241 | J5: =IF(I5<$B$4,I5+1,"") -> 46242 | K5: =IF(J5<$B$4,J5+1,"") -> 46243 | ... AG5: =IF(AF5<$B$4,AF5+1,"") -> 46265 | AH5: TOTAL DAYS | AI5: PRESENT | AJ5: HOLIDAY | AK5: WEEK OFF | AL5: ABESNT | AM5: HALF DAY | AN5: ON DUTY
C6: =TEXT(C5,"DDD") -> Sat | D6: =TEXT(D5,"DDD") -> Sun | E6: =TEXT(E5,"DDD") -> Mon | F6: =TEXT(F5,"DDD") -> Tue | G6: =TEXT(G5,"DDD") -> Wed | H6: =TEXT(H5,"DDD") -> Thu | I6: =TEXT(I5,"DDD") -> Fri | J6: =TEXT(J5,"DDD") -> Sat | ... AG6: =TEXT(AG5,"DDD") -> Mon
A8: emp01 | B8: Avinav sinha | C8: H | E8: A | F8: P | G8: HD | H8: OD | I8: P | J8: P | L8: A | M8: P | N8: HD | O8: OD | P8: P | Q8: H | S8: A | T8: P | U8: HD | V8: OD | W8: P | X8: P | Z8: A | AA8: P | AB8: HD | AC8: OD | AD8: P | AE8: P | AG8: OD | AH8: =COUNT(C$5:AG$5) -> 31 | AI8: =COUNTIF($C8:$AG8,"P") -> 11 | AJ8: =COUNTIF($C8:$AG8,"H") -> 2 | AK8: =COUNTIF(C$6:AG$7,"Sun") -> 5 | AL8: =COUNTIF($C8:$AG8,"A") -> 4 | AM8: =COUNTIF($C8:$AG8,"HD") -> 4 | AN8: =COUNTIF($C8:$AG8,"OD") -> 5
A9: emp02 | B9: Gaurav Singh | C9: H | E9: P | F9: P | G9: P | H9: P | I9: A | J9: HD | L9: P | M9: P | N9: P | O9: P | P9: A | Q9: H | S9: P | T9: P | U9: P | V9: P | W9: A | X9: HD | Z9: P | AA9: P | AB9: P | AC9: P | AD9: A | AE9: HD | AG9: HD | AH9: =COUNT(C$5:AG$5) -> 31 | AI9: =COUNTIF($C9:$AG9,"P") -> 16 | AJ9: =COUNTIF($C9:$AG9,"H") -> 2 | AK9: =COUNTIF(C$6:AG$7,"Sun") -> 5 | AL9: =COUNTIF($C9:$AG9,"A") -> 4 | AM9: =COUNTIF($C9:$AG9,"HD") -> 4 | AN9: =COUNTIF($C9:$AG9,"OD") -> 0
A10: emp03 | B10: Tushar Choubey | C10: H | E10: HD | F10: P | G10: OD | H10: P | I10: P | J10: P | L10: HD | M10: P | N10: OD | O10: P | P10: P | Q10: H | S10: HD | T10: P | U10: OD | V10: P | W10: P | X10: P | Z10: HD | AA10: P | AB10: OD | AC10: P | AD10: P | AE10: P | AG10: P | AH10: =COUNT(C$5:AG$5) -> 31 | AI10: =COUNTIF($C10:$AG10,"P") -> 16 | AJ10: =COUNTIF($C10:$AG10,"H") -> 2 | AK10: =COUNTIF(C$6:AG$7,"Sun") -> 5 | AL10: =COUNTIF($C10:$AG10,"A") -> 0 | AM10: =COUNTIF($C10:$AG10,"HD") -> 4 | AN10: =COUNTIF($C10:$AG10,"OD") -> 4

Sheet SALARY
A4: EMP_ID | B4: EMP_NAME | C4: DESIGNATION | D4: BASIC SALARY | E4: TOTAL DAYS | F4: ATTEDANCE (WORKING DAYS) | G4: PER DAY SALARY | H4: SALARY(BASED ON ATTENDANCE) | I4: DA(12%) | J4: CITY | K4: HRA | L4: TA | M4: OT IN HRS | N4: OVERTIME PAY | O4: GROSS SALARY | P4: PF (12%) | Q4: ESI (0.75%) | R4: NET SALARY
A5: =ATTENDANCE!A8 -> emp01 | B5: =ATTENDANCE!B8 -> Avinav sinha | C5: officer | D5: 30000 | E5: =ATTENDANCE!AH8 -> 31 | F5: =SUM(ATTENDANCE!AI8:AK8) -> 18 | G5: =D5/E5 -> 967.74194 | H5: =G5*F5 -> 17419.355 | I5: =D5*12% -> 3600 | J5: NON METRO | K5: =IF(J5="METRO",D5*50%,D5*40%) -> 12000 | L5: 1000 | M5: 3 | N5: =G5/9*M5 -> 322.58065 | O5: =H5+I5+K5+L5 -> 34019.355 | P5: =12%*D5 -> 3600 | Q5: =IF(O5<=21000,O5*0.75%,"N/A") -> N/A | R5: =IF(ISNUMBER(Q5),O5-P5-Q5,O5-P5) -> 30419.355
A6: =ATTENDANCE!A9 -> emp02 | B6: =ATTENDANCE!B9 -> Gaurav Singh | C6: Manger | D6: 50000 | E6: =ATTENDANCE!AH9 -> 31 | F6: =SUM(ATTENDANCE!AI9:AK9) -> 23 | G6: =D6/E6 -> 1612.9032 | H6: =G6*F6 -> 37096.774 | I6: =D6*12% -> 6000 | J6: NON METRO | K6: =IF(J6="METRO",D6*50%,D6*40%) -> 20000 | L6: 1000 | M6: 0.5 | N6: =G6/9*M6 -> 89.605735 | O6: =H6+I6+K6+L6 -> 64096.774 | P6: =12%*D6 -> 6000 | Q6: =IF(O6<=21000,O6*0.75%,"N/A") -> N/A | R6: =IF(ISNUMBER(Q6),O6-P6-Q6,O6-P6) -> 58096.774
A7: =ATTENDANCE!A10 -> emp03 | B7: =ATTENDANCE!B10 -> Tushar Choubey | C7: Labour | D7: 10000 | E7: =ATTENDANCE!AH10 -> 31 | F7: =SUM(ATTENDANCE!AI10:AK10) -> 23 | G7: =D7/E7 -> 322.58065 | H7: =G7*F7 -> 7419.3548 | I7: =D7*12% -> 1200 | J7: NON METRO | K7: =IF(J7="METRO",D7*50%,D7*40%) -> 4000 | L7: 1000 | M7: 5 | N7: =G7/9*M7 -> 179.21147 | O7: =H7+I7+K7+L7 -> 13619.355 | P7: =12%*D7 -> 1200 | Q7: =IF(O7<=21000,O7*0.75%,"N/A") -> 102.14516 | R7: =IF(ISNUMBER(Q7),O7-P7-Q7,O7-P7) -> 12317.21

Sheet SLIP
A2: ABC Services Private Limited
A3: 197 F2 SAKET NAGAR BHOPAL - 462024
A5: EMPLOYEE DETAILS | C5: SALARY DETAILS
A6: EMP_ID | B6: emp01 | C6: TOTAL DAYS | D6: =VLOOKUP($B$6,SALARY!$A:$R,5,0) -> 31
A7: EMP_NAME | B7: =VLOOKUP($B$6,SALARY!$A:$R,2,0) -> Avinav sinha | C7: ATTENDANCE | D7: =VLOOKUP($B$6,SALARY!$A:$R,6,0) -> 18
A8: DESIGNATION | B8: =VLOOKUP($B$6,SALARY!$A:$R,3,0) -> officer | C8: SLIP PRINT DATE | D8: =TODAY() -> 46254
A9: BASIC SALARY
A10: EARNINGS | C10: DEDUCTIONS
A11: salary (based on attendance) | B11: =VLOOKUP($B$6,SALARY!$A:$R,8,0) -> 17419.355 | C11: PF(12%) | D11: =VLOOKUP($B$6,SALARY!$A:$R,16,0) -> 3600
A12: DA(12%) | B12: =VLOOKUP($B$6,SALARY!$A:$R,9,0) -> 3600 | C12: ESI(0.75%) | D12: =VLOOKUP($B$6,SALARY!$A:$R,17,0) -> N/A
A13: HRA | B13: =VLOOKUP($B$6,SALARY!$A:$R,11,0) -> 12000 | C13: Loan | D13: 0
A14: TA | B14: =VLOOKUP($B$6,SALARY!$A:$R,12,0) -> 1000 | C14: Tax | D14: 0
A15: Overtime Pay | B15: =VLOOKUP($B$6,SALARY!$A:$R,14,0) -> 322.58065
A16: Gross Salary | B16: =SUM(B11:B15) -> 34341.935 | C16: Gross Deduction | D16: =SUM(D11:D15) -> 3600
A17: NET SALARY | C17: =B16-D16 -> 30741.935

Sheet Months
A1: January
A2: February
A3: March
A4: April
A5: May
A6: June
A7: July
A8: August
A9: September
A10: October
A11: November
A12: December
